setup.cfg
setup.py
guardiancl/__init__.py
guardiancl/account.py
guardiancl/console.py
guardiancl/device.py
guardiancl/guardianService.py
guardiancl/run.py
guardiancl/utils.py
guardiancl.egg-info/PKG-INFO
guardiancl.egg-info/SOURCES.txt
guardiancl.egg-info/dependency_links.txt
guardiancl.egg-info/entry_points.txt
guardiancl.egg-info/not-zip-safe
guardiancl.egg-info/requires.txt
guardiancl.egg-info/top_level.txt