Metadata-Version: 1.1
Name: guardiancl
Version: 0.0.6
Summary: Computer system information for GuardianCL
Home-page: https://github.com/guardiaocl/guardiaocl-servers.git
Author: WeboneSystem
Author-email: suporte@webonesystem.com.br
License: Apache
Keywords: monitoring web iot
Platform: UNKNOWN
Classifier: Topic :: System :: Monitoring
Classifier: Topic :: System :: Logging
Classifier: Topic :: System :: Networking :: Monitoring
Classifier: Development Status :: 4 - Beta
Classifier: Programming Language :: Python
Classifier: License :: OSI Approved :: Apache Software License
Classifier: Intended Audience :: Developers
Classifier: Intended Audience :: System Administrators
Classifier: Programming Language :: Python :: 2.7
